ngoschema/__init__.py
ngoschema/decorators.py
ngoschema/exceptions.py
ngoschema/query.py
ngoschema/registries.py
ngoschema/relationships.py
ngoschema/session.py
ngoschema/__pycache__/__init__.cpython-36.pyc
ngoschema/__pycache__/__init__.cpython-37.pyc
ngoschema/__pycache__/decorators.cpython-36.pyc
ngoschema/__pycache__/decorators.cpython-37.pyc
ngoschema/__pycache__/exceptions.cpython-36.pyc
ngoschema/__pycache__/exceptions.cpython-37.pyc
ngoschema/__pycache__/query.cpython-36.pyc
ngoschema/__pycache__/query.cpython-37.pyc
ngoschema/__pycache__/registries.cpython-36.pyc
ngoschema/__pycache__/registries.cpython-37.pyc
ngoschema/__pycache__/relationships.cpython-36.pyc
ngoschema/__pycache__/relationships.cpython-37.pyc
ngoschema/__pycache__/session.cpython-36.pyc
ngoschema/__pycache__/session.cpython-37.pyc
ngoschema/cli/__init__.py
ngoschema/cli/__pycache__/__init__.cpython-36.pyc
ngoschema/cli/__pycache__/__init__.cpython-37.pyc
ngoschema/config/__init__.py
ngoschema/config/settings.py
ngoschema/config/utils.py
ngoschema/config/__pycache__/__init__.cpython-36.pyc
ngoschema/config/__pycache__/__init__.cpython-37.pyc
ngoschema/config/__pycache__/settings.cpython-36.pyc
ngoschema/config/__pycache__/settings.cpython-37.pyc
ngoschema/config/__pycache__/utils.cpython-37.pyc
ngoschema/contexts/__init__.py
ngoschema/contexts/entity_context.py
ngoschema/contexts/instance_context.py
ngoschema/contexts/ns_manager_context.py
ngoschema/contexts/object_protocol_context.py
ngoschema/contexts/__pycache__/__init__.cpython-36.pyc
ngoschema/contexts/__pycache__/__init__.cpython-37.pyc
ngoschema/contexts/__pycache__/entity_context.cpython-36.pyc
ngoschema/contexts/__pycache__/entity_context.cpython-37.pyc
ngoschema/contexts/__pycache__/instance_context.cpython-36.pyc
ngoschema/contexts/__pycache__/instance_context.cpython-37.pyc
ngoschema/contexts/__pycache__/ns_manager_context.cpython-36.pyc
ngoschema/contexts/__pycache__/ns_manager_context.cpython-37.pyc
ngoschema-1.0.10.dist-info/AUTHORS.rst
ngoschema-1.0.10.dist-info/LICENSE
ngoschema-1.0.10.dist-info/METADATA
ngoschema-1.0.10.dist-info/WHEEL
ngoschema-1.0.10.dist-info/entry_points.txt
ngoschema-1.0.10.dist-info/top_level.txt
ngoschema-1.0.10.dist-info/RECORD
